classify_imports.py
classify_imports-4.2.0.dist-info/LICENSE
classify_imports-4.2.0.dist-info/METADATA
classify_imports-4.2.0.dist-info/WHEEL
classify_imports-4.2.0.dist-info/top_level.txt
classify_imports-4.2.0.dist-info/RECORD
